balic/__init__.py
balic/__main__.py
balic/build.py
balic/create.py
balic/destroy.py
balic/hosts.py
balic/ls.py
balic/main.py
balic/pack.py
balic/prepare.py
tests/__init__.py
tests/test_balic.py
tests/test_main.py
balic-0.0.8.dist-info/LICENSE
balic-0.0.8.dist-info/METADATA
balic-0.0.8.dist-info/WHEEL
balic-0.0.8.dist-info/entry_points.txt
balic-0.0.8.dist-info/namespace_packages.txt
balic-0.0.8.dist-info/top_level.txt
balic-0.0.8.dist-info/RECORD
