Metadata-Version: 2.1
Name: balic
Version: 0.0.8
Summary: Balic - Command-line Linux Containers Toolset
Home-page: https://gitlab.com/markuz/balic
Author: Marek Kuziel
Author-email: marek@kuziel.info
License: UNKNOWN
Download-URL: https://gitlab.com/markuz/balic/-/archive/master/balic-master.tar.bz2
Platform: Any
Classifier: Development Status :: 5 - Production/Stable
Classifier: License :: OSI Approved :: BSD License
Classifier: Programming Language :: Python
Classifier: Programming Language :: Python :: 3
Classifier: Programming Language :: Python :: 3.7
Classifier: Programming Language :: Python :: 3.8
Classifier: Intended Audience :: Other Audience
Classifier: Environment :: Console
Requires-Dist: appdirs
Requires-Dist: cliff
Requires-Dist: sarge
Requires-Dist: pyyaml (>5)
Requires-Dist: proxmoxer
Requires-Dist: paramiko
Requires-Dist: requests
